koumura/__about__.py
koumura/__init__.py
koumura/koumura.py
koumura-0.2.1.post1.dist-info/LICENSE
koumura-0.2.1.post1.dist-info/WHEEL
koumura-0.2.1.post1.dist-info/METADATA
koumura-0.2.1.post1.dist-info/RECORD
