Metadata-Version: 2.1
Name: koumura
Version: 0.2.1.post1
Summary: Functions for working with this data repository: https://figshare.com/articles/BirdsongRecognition/3470165
Home-page: https://github.com/NickleDave/koumura
License: BSD
Author: David Nicholson
Author-email: nickledave@users.noreply.github.com
Requires-Python: >=3.6
Classifier: Development Status :: 5 - Production/Stable
Classifier: License :: OSI Approved :: BSD License
Classifier: License :: Other/Proprietary License
Classifier: Programming Language :: Python
Classifier: Programming Language :: Python :: 3
Classifier: Programming Language :: Python :: 3.6
Classifier: Programming Language :: Python :: 3.7
Classifier: Programming Language :: Python :: 3.8
Classifier: Programming Language :: Python :: 3.9
Classifier: Programming Language :: Python :: Implementation :: CPython
Requires-Dist: numpy (>=1.18.1)
Project-URL: Repository, https://github.com/NickleDave/koumura
